django_utils/__init__.py
django_utils/apps.py
django_utils/authentication/__init__.py
django_utils/db/__init__.py
django_utils/db/fields/__init__.py
django_utils/db/fields/text.py
django_utils/management/__init__.py
django_utils/management/commands/__init__.py
django_utils/management/commands/sentry_test.py
django_utils/serializer/__init__.py
django_utils/serializer/fields/__init__.py
django_utils/serializer/fields/protected_image_field.py
django_utils/settings/__init__.py
django_utils/settings/logging.py
django_utils/settings/sentry.py
django_utils/testing/__init__.py
django_utils/testing/filestructure.py
django_utils/testing/urls.py
django_utils/testing/views.py
django_utils/views/__init__.py
django_utils/views/file_getter.py
django_utils/webhooks/__init__.py
django_utils/webhooks/delete_user/__init__.py
django_utils/webhooks/delete_user/default_delete_hooks.py
django_utils/webhooks/delete_user/serializers.py
django_utils/webhooks/delete_user/token_authentication.py
django_utils/webhooks/delete_user/urls.py
django_utils/webhooks/delete_user/views.py
ftw_django_utils-2025.2.0.dist-info/LICENSE
ftw_django_utils-2025.2.0.dist-info/METADATA
ftw_django_utils-2025.2.0.dist-info/WHEEL
ftw_django_utils-2025.2.0.dist-info/RECORD
