Metadata-Version: 2.3
Name: ftw-django-utils
Version: 2025.2.0
Summary: A collection of utils used in our Django based web applications.
Author: 4teamwork AG
Requires-Python: >=3.12,<4
Classifier: Programming Language :: Python :: 3
Classifier: Programming Language :: Python :: 3.12
Classifier: Programming Language :: Python :: 3.13
Requires-Dist: django (>=4,<5)
Requires-Dist: django-configurations (>=2.5,<3.0)
Requires-Dist: django-extensions (>=4,<5)
Requires-Dist: django-sendfile2 (>=0.7,<0.8)
Requires-Dist: djangorestframework (>=3,<4)
Requires-Dist: sentry-sdk
